ni_measurement_plugin_generator/__main__.py
ni_measurement_plugin_generator/py.typed
ni_measurement_plugin_generator/template.py
ni_measurement_plugin_generator/templates/_helpers.py.mako
ni_measurement_plugin_generator/templates/measurement.measproj.mako
ni_measurement_plugin_generator/templates/measurement.measui.mako
ni_measurement_plugin_generator/templates/measurement.py.mako
ni_measurement_plugin_generator/templates/measurement.serviceconfig.mako
ni_measurement_plugin_generator/templates/start.bat.mako
ni_measurement_plugin_generator-2.0.0.dev0.dist-info/METADATA
ni_measurement_plugin_generator-2.0.0.dev0.dist-info/WHEEL
ni_measurement_plugin_generator-2.0.0.dev0.dist-info/entry_points.txt
ni_measurement_plugin_generator-2.0.0.dev0.dist-info/RECORD
