Metadata-Version: 2.1
Name: ni_measurement_plugin_generator
Version: 2.0.0.dev0
Summary: Measurement Plugin Code Generator for Python
Home-page: https://github.com/ni/measurementlink-python/
License: MIT
Author: NI
Author-email: opensource@ni.com
Requires-Python: >=3.8,<4.0
Classifier: Development Status :: 5 - Production/Stable
Classifier: Intended Audience :: Developers
Classifier: Intended Audience :: Manufacturing
Classifier: Intended Audience :: Science/Research
Classifier: License :: OSI Approved :: MIT License
Classifier: Operating System :: Microsoft :: Windows
Classifier: Programming Language :: Python :: 3
Classifier: Programming Language :: Python :: 3.8
Classifier: Programming Language :: Python :: 3.9
Classifier: Programming Language :: Python :: 3.10
Classifier: Programming Language :: Python :: 3.11
Classifier: Programming Language :: Python :: 3.12
Classifier: Programming Language :: Python :: Implementation :: CPython
Classifier: Topic :: Scientific/Engineering
Classifier: Topic :: System :: Hardware
Requires-Dist: Mako (>=1.2.1,<2.0.0)
Requires-Dist: click (>=8.1.3)
Project-URL: Repository, https://github.com/ni/measurementlink-python/
